{"name":"Andygator","abv":8.0,"ibu":0.0,"srm":0.0,"upc":0,"type":"beer","brewery_id":"abita_brewing_company","updated":"2010-07-22 20:00:20","description":"The Andygator is a fearsome beast...much too big for any little bottle. Don't let his toothy grin, slightly sweet flavor and subtle fruit aroma fool you: this cold-blooded creature is a Helles Doppelbock that can sneak up on you. Sip, don't gulp and taste the wild of Abita Andygator","style":"German-Style Doppelbock","category":"German Lager"}