{"name":"Scape Goat Pale Ale","abv":4.7,"ibu":0.0,"srm":0.0,"upc":0,"type":"beer","brewery_id":"big_sky_brewing","updated":"2010-07-22 20:00:20","description":"Scape Goat is our award-winning Pale Ale. It is a very smooth brew, refreshing and well-balanced. Scape Goat took home the Gold Medal from the North American Brewers' Association competitions as the best English-style pale ale brewed west of the Mississippi, but only because it is the best. Scape Goat is brewed with pale, crystal malts, and Kent Goldings and Crystal Hops. Scape Goat is 3.8% alcohol by weight and 4.7% by volume.","style":"American-Style Pale Ale","category":"North American Ale"}