{"name":"Dogtoberfest Octoberfest","abv":5.3,"ibu":0.0,"srm":0.0,"upc":0,"type":"beer","brewery_id":"flying_dog_brewery","updated":"2010-07-22 20:00:20","description":"Dogtoberfest are shrouded in mystery, but scholars think it has everything to do with an insane German king and a crazed Oompah band. You can read the full historical record of Dogtoberfest at FlyingDogAles.com. Dogtoberfest is deep mahogany in color with an intriguing caramel finish and brewed with 100% imported German ingredients for a true German flavor.","style":"German-Style Oktoberfest","category":"German Lager"}