{"name":"Big Bark Amber Lager","abv":0.0,"ibu":0.0,"srm":0.0,"upc":0,"type":"beer","brewery_id":"live_oak_brewing","updated":"2010-07-22 20:00:20","description":"\"Smooth\" is the first word from your mouth after a taste of Big Bark Amber. This Vienna-style lager has a reddish-amber color with a smooth, malty flavor and low hop bitterness. It is made from Czech and German malts and German hops. \"All Bark, No Bite.\" Everyone likes this beer.","style":"American-Style Lager","category":"North American Lager"}