{"name":"St. Patrick's Gold","abv":4.8,"ibu":0.0,"srm":0.0,"upc":0,"type":"beer","brewery_id":"strangford_lough_brewing_company_ltd","updated":"2010-07-22 20:00:20","description":"Our smooth yet powerful wheat beer is unusually refreshing on the pallet.  Golden in colour, St. Patrick's Gold is brewed with barley and wheat malt. Citrus peel and coriander are added to the Goldings and Saaz hops for a symphony of authentic flavour.","style":"Light American Wheat Ale or Lager","category":"Other Style"}