{"name":"Avant Garde","abv":7.0,"ibu":0.0,"srm":0.0,"upc":0,"type":"beer","brewery_id":"the_lost_abbey","updated":"2010-07-22 20:00:20","description":"From the French word “Garde” meaning something worth keeping, this Biere de Garde styled Farmhouse Ale is a most delicious companion to a loaf of freshly baked bread from the oven. Grab a seat on the porch, some soft cheese and a tree ripened apple from your grandmother’s old orchard. Relax and watch the evening arrive as the afternoon sun is consumed by the illuminating moon over the gardens. We brewed Avant Garde for you, our friends and families. Here’s to things worth guarding over.","style":"French & Belgian-Style Saison","category":"Belgian and French Ale"}