{"name":"St. Boisterous Hellerbock","abv":7.3,"ibu":0.0,"srm":0.0,"upc":0,"type":"beer","brewery_id":"victory_brewing","updated":"2010-07-22 20:00:20","description":"A full-bodied lager beer of exuberant and robust character. It’s muscle-man body comes from decocted German malts and noble German hops. Lagered long and cold to refine its strong temperament, St. Boisterous emerges smooth and seductive, with a malty sweet charm. This classic rendition of the German ‘maibock' style will warm your heart.","style":"German-Style Heller Bock/Maibock","category":"German Lager"}