{"name":"Widmer W'08","abv":4.9,"ibu":0.0,"srm":0.0,"upc":0,"type":"beer","brewery_id":"widmer_brothers_brewing","updated":"2010-07-22 20:00:20","description":"\"Our Brewmasters' Release - The three different red, caramelized, and dark wheat malts give this beer an intense red color that runs as deep as the flavor. The toasted grain flavors blend perfectly with the subtle spiciness of the hops just as the entirety fades to a smooth quick finish. 2007 Great American Beer Festival Silver Medal Award Winner.\"\r\n-Widmer Brothers Brewing Company","style":"Light American Wheat Ale or Lager","category":"Other Style"}